redirect_webfinger/__init__.py
redirect_webfinger/__main__.py
redirect_webfinger-0.0.6.dist-info/COPYING
redirect_webfinger-0.0.6.dist-info/METADATA
redirect_webfinger-0.0.6.dist-info/WHEEL
redirect_webfinger-0.0.6.dist-info/entry_points.txt
redirect_webfinger-0.0.6.dist-info/top_level.txt
redirect_webfinger-0.0.6.dist-info/RECORD
