Metadata-Version: 2.1
Name: redirect-webfinger
Version: 0.0.6
Summary: Basic implementation of webfinger that redirects to another server
Home-page: https://github.com/jelmer/redirect-webfinger
Author: Jelmer Vernooĳ
Author-email: jelmer@jelmer.uk
License: Apachev2
Classifier: Development Status :: 4 - Beta
Classifier: License :: OSI Approved :: Apache Software License
Classifier: Programming Language :: Python :: 3.9
Classifier: Programming Language :: Python :: 3.10
Classifier: Programming Language :: Python :: Implementation :: CPython
Classifier: Programming Language :: Python :: Implementation :: PyPy
Classifier: Operating System :: POSIX
Requires-Python: >=3.9
License-File: COPYING
Requires-Dist: aiohttp
Requires-Dist: aiohttp-openmetrics
